template_flask/__init__.py
template_flask/__main__.py
template_flask/constants.py
template_flask/funcs.py
template_flask/test_test.py
template_flask/bootstrap/static/css/blog.css
template_flask/bootstrap/static/css/bootstrap.min.css
template_flask/bootstrap/static/css/bootstrap.min.css.map
template_flask/bootstrap/static/css/carousel.css
template_flask/bootstrap/static/css/cheatsheet.css
template_flask/bootstrap/static/css/checkout.css
template_flask/bootstrap/static/css/cover.css
template_flask/bootstrap/static/css/dashboard.css
template_flask/bootstrap/static/css/grid.css
template_flask/bootstrap/static/css/headers.css
template_flask/bootstrap/static/css/heroes.css
template_flask/bootstrap/static/css/navbar_top_fixed.css
template_flask/bootstrap/static/css/navbar_top_static.css
template_flask/bootstrap/static/css/navbars.css
template_flask/bootstrap/static/css/pricing.css
template_flask/bootstrap/static/css/product.css
template_flask/bootstrap/static/css/sidebars.css
template_flask/bootstrap/static/css/sign_in.css
template_flask/bootstrap/static/css/starter_template.css
template_flask/bootstrap/static/css/sticky_footer.css
template_flask/bootstrap/static/css/sticky_footer_navbar.css
template_flask/bootstrap/static/js/bootstrap.bundle.min.js
template_flask/bootstrap/static/js/bootstrap.bundle.min.js.map
template_flask/bootstrap/static/js/cheatsheet.js
template_flask/bootstrap/static/js/checkout.js
template_flask/bootstrap/static/js/dashboard.js
template_flask/bootstrap/static/js/sidebars.js
template_flask/bootstrap/templates/album.html
template_flask/bootstrap/templates/blog.html
template_flask/bootstrap/templates/carousel.html
template_flask/bootstrap/templates/cheatsheet.html
template_flask/bootstrap/templates/checkout.html
template_flask/bootstrap/templates/cover.html
template_flask/bootstrap/templates/dashboard.html
template_flask/bootstrap/templates/grid.html
template_flask/bootstrap/templates/headers.html
template_flask/bootstrap/templates/heroes.html
template_flask-3.3.dist-info/LICENSE.txt
template_flask-3.3.dist-info/METADATA
template_flask-3.3.dist-info/WHEEL
template_flask-3.3.dist-info/top_level.txt
template_flask-3.3.dist-info/RECORD
