Metadata-Version: 2.1
Name: template-flask
Version: 3.3
Summary: Python module for creating a template flask app structure and virtual environment, along with Bootstrap examples
Home-page: https://github.com/zacharybeebe/template_flask
Author: Zach Beebe
Author-email: z.beebe@yahoo.com
License: MIT
Keywords: flask,directory structure,cookie cuttervenv,bootstrap
Classifier: Development Status :: 5 - Production/Stable
Classifier: Intended Audience :: Science/Research
Classifier: Programming Language :: Python :: 3
Classifier: License :: OSI Approved :: MIT License
Classifier: Operating System :: OS Independent
Requires-Python: >=3.6
License-File: LICENSE.txt
